[{"id":"e659a1d3.91cdf","type":"tab","label":"Flow 2","disabled":false,"info":""},{"id":"289c69f6.e9d076","type":"function","z":"e659a1d3.91cdf","name":"","func":"msg.payload=msg.payload.text;\nreturn msg;","outputs":1,"noerr":0,"initialize":"","finalize":"","x":300,"y":260,"wires":[["4f9dc05a.6722f","d7398cdd.96a4c"]]},{"id":"4f9dc05a.6722f","type":"ui_text","z":"e659a1d3.91cdf","group":"1306a2c1.369c4d","order":3,"width":0,"height":0,"name":"","label":"you","format":"{{msg.payload}}","layout":"col-center","x":430,"y":380,"wires":[]},{"id":"4c3170de.3b79","type":"debug","z":"e659a1d3.91cdf","name":"","active":true,"tosidebar":true,"console":false,"tostatus":false,"complete":"payload","targetType":"msg","statusVal":"","statusType":"auto","x":760,"y":200,"wires":[]},{"id":"21f9c890.fac178","type":"ui_form","z":"e659a1d3.91cdf","name":"","label":"","group":"1306a2c1.369c4d","order":5,"width":0,"height":0,"options":[{"label":"Enter input","value":"text","type":"text","required":true,"rows":null}],"formValue":{"text":""},"payload":"","submit":"submit","cancel":"cancel","topic":"","x":90,"y":320,"wires":[["289c69f6.e9d076"]]},{"id":"d7398cdd.96a4c","type":"watson-conversation-v1","z":"e659a1d3.91cdf","name":"ss","workspaceid":"bda1cf29-896a-474a-a472-7273529f3b64","multiuser":false,"context":true,"empty-payload":false,"service-endpoint":"https://api.eu-gb.assistant.watson.cloud.ibm.com/instances/4ffb41f6-7296-4143-a78d-80fd8d13307f","timeout":"","optout-learning":false,"x":450,"y":180,"wires":[["4c3170de.3b79","4e621c47.159ee4"]]},{"id":"b436da54.24e6a8","type":"ui_template","z":"e659a1d3.91cdf","group":"1306a2c1.369c4d","name":"smartbot","order":6,"width":"6","height":"42","format":"<div ng-bind-html=\"msg.payload\"></div>","storeOutMessages":true,"fwdInMessages":true,"resendOnRefresh":true,"templateScope":"local","x":740,"y":100,"wires":[[]]},{"id":"a08b791.8e2a588","type":"template","z":"e659a1d3.91cdf","name":"","field":"payload","fieldType":"msg","format":"handlebars","syntax":"mustache","template":"<ul>\n{{#payload}}\n  <li>{{.}}</li>\n{{/payload}}\n</ul>","output":"str","x":500,"y":80,"wires":[["b436da54.24e6a8"]]},{"id":"4e621c47.159ee4","type":"function","z":"e659a1d3.91cdf","name":"","func":"msg.payload=msg.payload.output.text;\nreturn msg;","outputs":1,"noerr":0,"initialize":"","finalize":"","x":600,"y":140,"wires":[["a08b791.8e2a588"]]},{"id":"1306a2c1.369c4d","type":"ui_group","z":"","name":"Home","tab":"a5fab777.542728","order":1,"disp":true,"width":"6","collapse":false,"disabled":false,"hidden":false},{"id":"a5fab777.542728","type":"ui_tab","z":"","name":"chatbot","icon":"dashboard","disabled":false,"hidden":false}]